MANIFEST.in
NOTICE.txt
README.rst
bootstrap.py
buildout.cfg
setup.py
docs/HISTORY.txt
docs/INSTALL.txt
docs/LICENSE.txt
docs/USE.txt
edrn/__init__.py
edrn.sync.egg-info/PKG-INFO
edrn.sync.egg-info/SOURCES.txt
edrn.sync.egg-info/dependency_links.txt
edrn.sync.egg-info/entry_points.txt
edrn.sync.egg-info/namespace_packages.txt
edrn.sync.egg-info/requires.txt
edrn.sync.egg-info/top_level.txt
edrn.sync.egg-info/zip-safe
edrn/sync/__init__.py
edrn/sync/dmccmakegroups.py
edrn/sync/dmccsync.py
edrn/sync/oldpasswords.py
edrn/sync/rdf.py
edrn/sync/syncldap.py
edrn/sync/utils.py
edrn/sync/conf/__init__.py
edrn/sync/profiles/default/rdf/dmcc-committes.rdf
edrn/sync/profiles/default/rdf/dmcc-sites.rdf
edrn/sync/profiles/default/rdf/dmcc-users.rdf
edrn/sync/tests/__init__.py
edrn/sync/tests/testClasses.py
edrn/sync/tests/testFunctions.py
edrn/sync/tests/data/bad.rdf
edrn/sync/tests/data/bad.xml
edrn/sync/tests/data/committees.rdf
edrn/sync/tests/data/no-email.rdf
edrn/sync/tests/data/sites.rdf
edrn/sync/tests/data/users.rdf