Metadata-Version: 2.1
Name: edrn.sync
Version: 1.0.5
Summary: EDRN Sync Services
Home-page: https://github.com/EDRN/edrn.sync
Author: Chris Mattmann
Author-email: chris.a.mattmann@jpl.nasa.gov
License: Copyright 2008-2019 by the California Institute of Technology.  ALL RIGHTS
